{"600585.SH":"日低进了，日高出","002714.SZ":"","600887.SH":"月高出","603568.SH":"装备制造收入占比增加，但行业装机量增速下滑，应收较高","600132.SH":"日高出","600566.SH":"日高出两手","002508.SZ":"坐等分红","600886.SH":"现金牛、自然垄断","002158.SZ":"存货略高，高管减持","002223.SZ":"产品种类太多，所处行业竞争激烈","600660.SH":"已卖出两手","603338.SH":"一季度超预期，等周高点","002832.SZ":"业绩略下滑，符合预期，PE 12，股息 3%","603556.SH":"一季报不及预期，第二天跌停，加仓（04/30）","600309.SH":"","688016.SH":"","000858.SZ":"等周/月低点","603444.SH":"","300760.SZ":"红肥绿瘦，已加仓一手（04/30）","603259.SH":"已卖出两手，等周月高点","000651.SZ":"年报一季报超预期，分红超预期","002027.SZ":"基本符合预期，04/29 如果能低开或高开不多就加仓（高开 3 个点，没加进去）"}